hiworkflow-2.6.dist-info/metadata.json
hiworkflow-2.6.dist-info/METADATA
hiworkflow-2.6.dist-info/DESCRIPTION.rst
hiworkflow-2.6.dist-info/RECORD
hiworkflow-2.6.dist-info/top_level.txt
hiworkflow-2.6.dist-info/WHEEL
workflowapp/admin.pyc
workflowapp/__init__.pyc
workflowapp/views.py
workflowapp/tests.pyc
workflowapp/tests.py
workflowapp/models.py
workflowapp/models.pyc
workflowapp/admin.py
workflowapp/apps.py
workflowapp/createflow.pyc
workflowapp/views.pyc
workflowapp/createflow.py
workflowapp/__init__.py
workflowapp/migrations/__init__.pyc
workflowapp/migrations/0005_auto_20160308_1403.py
workflowapp/migrations/0001_initial.py
workflowapp/migrations/0002_trigger.py
workflowapp/migrations/0010_state_is_automated.pyc
workflowapp/migrations/0001_initial.pyc
workflowapp/migrations/0006_assignee_assigned_by.py
workflowapp/migrations/0004_auto_20160308_0952.pyc
workflowapp/migrations/0009_auto_20160310_1331.pyc
workflowapp/migrations/0007_auto_20160309_1223.py
workflowapp/migrations/0005_auto_20160308_1403.pyc
workflowapp/migrations/0004_auto_20160308_0952.py
workflowapp/migrations/0006_assignee_assigned_by.pyc
workflowapp/migrations/0002_trigger.pyc
workflowapp/migrations/__init__.py
workflowapp/migrations/0007_auto_20160309_1223.pyc
workflowapp/migrations/0010_state_is_automated.py
workflowapp/migrations/0009_auto_20160310_1331.py
workflowapp/migrations/0003_auto_20160308_0709.py
workflowapp/migrations/0008_auto_20160309_1228.pyc
workflowapp/migrations/0003_auto_20160308_0709.pyc
workflowapp/migrations/0008_auto_20160309_1228.py
workflowapp/templates/index.html
workflowapp/templates/visualize.html
workflowapp/static/jquery.min.js
workflowapp/static/joint.css
workflowapp/static/lodash.min.js
workflowapp/static/joint.shapes.org.js
workflowapp/static/joint.js
workflowapp/static/backbone-min.js
