Metadata-Version: 2.0
Name: hiworkflow
Version: 2.6
Summary: A Django app to build and use custom Workflows.
Home-page: http://www.hashedin.com/
Author: Anshit
Author-email: anshit.agarwal@hashedin.com
License: MIT License
Platform: UNKNOWN
Classifier: Environment :: Web Environment
Classifier: Framework :: Django
Classifier: Intended Audience :: Developers
Classifier: License :: OSI Approved :: MIT License
Classifier: Operating System :: OS Independent
Classifier: Programming Language :: Python
Classifier: Programming Language :: Python :: 2.6
Classifier: Programming Language :: Python :: 2.7
Classifier: Topic :: Internet :: WWW/HTTP
Classifier: Topic :: Internet :: WWW/HTTP :: Dynamic Content
